InterviewTranscriber-0.0.2.dist-info/METADATA
InterviewTranscriber-0.0.2.dist-info/RECORD
InterviewTranscriber-0.0.2.dist-info/WHEEL
InterviewTranscriber-0.0.2.dist-info/top_level.txt
TestCases/__init__.py
TestCases/test_Transcriber.py
Transcriber/__init__.py
Transcriber/Google/Base.py
Transcriber/Google/Storage.py
Transcriber/Google/Transcriber.py
Transcriber/Google/__init__.py
