Metadata-Version: 2.1
Name: InterviewTranscriber
Version: 0.0.2
Summary: Python based interface for interacting with Google Cloud's Speech-to-Text API and Cloud Storage API.
Home-page: https://github.com/mjfox3/InterviewTranscriber
Author: Michael Joseph Fox
Author-email: mjfox3@ncsu.edu
License: UNKNOWN
Project-URL: Bug Reports, https://github.com/mjfox3/InterviewTranscriber/issues
Project-URL: Source, https://github.com/mjfox3/InterviewTranscriber
Keywords: sociolinguistics,linguistics,automatic analysis,transcription,textgrids
Platform: UNKNOWN
Requires-Python: >=3.6
Requires-Dist: google (==2.0.2)
Requires-Dist: google-api-core (==1.14.3)
Requires-Dist: google-auth (==1.6.3)
Requires-Dist: google-cloud-speech (==1.2.0)
Requires-Dist: googleapis-common-protos (==1.6.0)
Requires-Dist: pandas (==0.25.3)
Requires-Dist: TextGrid (==1.4)
